Flask_Lint-0.1.dev20171129.dist-info/DESCRIPTION.rst
Flask_Lint-0.1.dev20171129.dist-info/LICENSE.txt
Flask_Lint-0.1.dev20171129.dist-info/METADATA
Flask_Lint-0.1.dev20171129.dist-info/RECORD
Flask_Lint-0.1.dev20171129.dist-info/WHEEL
Flask_Lint-0.1.dev20171129.dist-info/metadata.json
Flask_Lint-0.1.dev20171129.dist-info/top_level.txt
flask_lint/__init__.py
flask_lint/i18n.py
flask_lint/lint.py
